{
    "ensemble0": {
        "mass0": {
            "T_strt": 10,
            "T_end": 25,
            "chi2": 0.9889714964585083,
            "Q": 0.4653426431553107,
            "mp": "3.7098(38)",
            "mp2": "4.100(60)",
            "c1": "9.080(97)e+05",
            "c2": "-9.23(30)e+05"
        }
    },
    "ensemble1": {
        "mass0": {
            "T_strt": 8,
            "T_end": 24,
            "chi2": 0.9889714964585083,
            "Q": 0.4653426431553107,
            "mp": "3.7098(38)",
            "mp2": "4.100(60)",
            "c1": "9.080(97)e+05",
            "c2": "-8.23(30)e+05"
        }
    },
    "ensemble2": {
        "mass1": {
            "T_strt": 8,
            "T_end": 23,
            "chi2": 0.9889714964585083,
            "Q": 0.4653426431553107,
            "mp": "3.7098(38)",
            "mp2": "4.100(60)",
            "c1": "2.080(97)e+06",
            "c2": "-2.23(30)e+06"
        }
    },
    "ensemble3": {
        "mass0": {
            "T_strt": 8,
            "T_end": 30,
            "chi2": 0.9889714964585083,
            "Q": 0.4653426431553107,
            "mp": "3.7098(38)",
            "mp2": "4.100(60)",
            "c1": "2.080(97)e+06",
            "c2": "-2.23(30)e+06"
        }
    },
    "ensemble4": {
        "mass0": {
            "T_strt": 5,
            "T_end": 18,
            "chi2": 0.9889714964585083,
            "Q": 0.4653426431553107,
            "mp": "3.7098(38)",
            "mp2": "4.100(60)",
            "c1": "7.080(97)e+06",
            "c2": "-6.23(30)e+06"
        }
    },
    "ensemble5": {
        "mass0": {
            "T_strt": 8,
            "T_end": 25,
            "chi2": 0.9889714964585083,
            "Q": 0.4653426431553107,
            "mp": "3.7098(38)",
            "mp2": "4.100(60)",
            "c1": "7.080(97)e+06",
            "c2": "-7.23(30)e+06"
        }
    },
    "ensemble6": {
        "mass0": {
            "T_strt": 10,
            "T_end": 25,
            "chi2": 0.9889714964585083,
            "Q": 0.4653426431553107,
            "mp": "3.7098(38)",
            "mp2": "4.100(60)",
            "c1": "2.080(97)e+06",
            "c2": "-1.63(30)e+06"
        }
    },
    "ensemble7": {
        "mass1": {
            "T_strt": 8,
            "T_end": 32,
            "chi2": 0.9889714964585083,
            "Q": 0.4653426431553107,
            "mp": "3.7098(38)",
            "mp2": "4.100(60)",
            "c1": "9.080(97)e+06",
            "c2": "-7.23(30)e+06"
        }
    },
    "ensemble8": {
        "mass0": {
            "T_strt": 6,
            "T_end": 20,
            "chi2": 0.9889714964585083,
            "Q": 0.4653426431553107,
            "mp": "3.7098(38)",
            "mp2": "4.100(60)",
            "c1": "2.080(97)e+06",
            "c2": "-1.93(30)e+06"
        }
    },
    "ensemble9": {
        "mass0": {
            "T_strt": 8,
            "T_end": 25,
            "chi2": 0.9889714964585083,
            "Q": 0.4653426431553107,
            "mp": "3.7098(38)",
            "mp2": "4.100(60)",
            "c1": "7.080(97)e+06",
            "c2": "-6.23(30)e+06"
        }
    },
    "ensemble10": {
        "mass0": {
            "T_strt": 10,
            "T_end": 35,
            "chi2": 0.9889714964585083,
            "Q": 0.4653426431553107,
            "mp": "3.7098(38)",
            "mp2": "4.300(60)",
            "c1": "7.280(97)e+06",
            "c2": "-4.83(30)e+06"
        }
    },
    "ensemble11": {
        "mass0": {
            "T_strt": 7,
            "T_end": 16,
            "chi2": 0.9889714964585083,
            "Q": 0.4653426431553107,
            "mp": "3.7098(38)",
            "mp2": "4.100(60)",
            "c1": "1.780(97)e+06",
            "c2": "-1.53(30)e+06"
        }
    },
    "ensemble12": {
        "mass0": {
            "T_strt": 10,
            "T_end": 32,
            "chi2": 0.9889714964585083,
            "Q": 0.4653426431553107,
            "mp": "3.7098(38)",
            "mp2": "4.200(60)",
            "c1": "3.380(97)e+06",
            "c2": "-1.73(30)e+06"
        }
    },
    "ensemble14": {
        "mass0": {
            "T_strt": 8,
            "T_end": 35,
            "chi2": 1.5636331941004573,
            "Q": 0.05169220934077797,
            "two_state_enabled": 1,
            "mp": "3.7098(38)",
            "mp2": "4.100(60)",
            "c1": "3.580(97)e+07",
            "c2": "-3.23(30)e+07"
        }
    }
}
