{
    "ensemble0": {
        "mass0": {
            "T_strt": 7,
            "T_end": 25,
            "chi2": 1.119959561612623,
            "Q": 0.3146421362580264,
            "mp": "3.6332(88)",
            "mp2": "4.06(10)",
            "c1": "893616(67627)",
            "c2": "-816246(98486)"
        }
    },
    "ensemble1": {
        "mass0": {
            "T_strt": 7,
            "T_end": 20,
            "chi2": 1.119959561612623,
            "Q": 0.3146421362580264,
            "mp": "3.5332(88)",
            "mp2": "4.06(10)",
            "c1": "823616(67627)",
            "c2": "-736246(98486)"
        }
    },
    "ensemble2": {
        "mass1": {
            "T_strt": 5,
            "T_end": 18,
            "chi2": 0.3622479075597696,
            "Q": 0.9901534167079823,
            "mp": "3.640(12)",
            "mp2": "4.04(18)",
            "c1": "1.89(27)e+06",
            "c2": "-2.00(69)e+06"
        }
    },
    "ensemble3": {
        "mass0": {
            "T_strt": 6,
            "T_end": 23,
            "chi2": 0.3622479075597696,
            "Q": 0.9901534167079823,
            "mp": "3.640(12)",
            "mp2": "4.04(18)",
            "c1": "1.89(27)e+06",
            "c2": "-2.00(69)e+06"
        }
    },
    "ensemble4": {
        "mass0": {
            "T_strt": 4,
            "T_end": 20,
            "chi2": 0.3622479075597696,
            "Q": 0.9901534167079823,
            "mp": "3.440(12)",
            "mp2": "4.04(18)",
            "c1": "7.29(27)e+06",
            "c2": "-6.40(69)e+06"
        }
    },
    "ensemble5": {
        "mass0": {
            "T_strt": 5,
            "T_end": 18,
            "chi2": 0.7926487694021264,
            "Q": 0.799532346079972,
            "mp": "3.616(13)",
            "mp2": "4.05(13)",
            "c1": "5.80(77)e+06",
            "c2": "-6.5(1.0)e+06"
        }
    },
    "ensemble6": {
        "mass0": {
            "T_strt": 8,
            "T_end": 22,
            "chi2": 0.7796134159591014,
            "Q": 0.8081443711990531,
            "mp": "3.6347(88)",
            "mp2": "4.23(19)",
            "c1": "1.81(14)e+06",
            "c2": "-1.98(72)e+06"
        }
    },
    "ensemble7": {
        "mass1": {
            "T_strt": 7,
            "T_end": 30,
            "chi2": 0.9872201152284761,
            "Q": 0.4871544869702116,
            "mp": "3.6321(68)",
            "mp2": "4.29(14)",
            "c1": "7.55(35)e+06",
            "c2": "-6.1(2.7)e+06"
        }
    },
    "ensemble8": {
        "mass0": {
            "T_strt": 7,
            "T_end": 23,
            "chi2": 0.8254201000672733,
            "Q": 0.6846254231759473,
            "mp": "3.609(10)",
            "mp2": "4.138(88)",
            "c1": "1.63(12)e+06",
            "c2": "-1.279(65)e+06"
        }
    },
    "ensemble9": {
        "mass0": {
            "T_strt": 6,
            "T_end": 20,
            "chi2": 0.9677480317116541,
            "Q": 0.5047130830886947,
            "mp": "3.612(11)",
            "mp2": "4.15(15)",
            "c1": "5.96(55)e+06",
            "c2": "-5.8(1.1)e+06"
        }
    },
    "ensemble10": {
        "mass0": {
            "T_strt": 13,
            "T_end": 40,
            "chi2": 1.3651242533619339,
            "Q": 0.06170335427200361,
            "two_state_enabled":1,
            "mp": "3.5497(96)",
            "mp2": "4.74(13)",
            "c1": "5.37(39)e+06",
            "c2": "-7.37415914(70)e+6"
        },
        "mass7": {
            "T_strt": 13,
            "T_end": 40,
            "chi2": 1.3651242533619339,
            "Q": 0.06170335427200361,
            "two_state_enabled":1,
            "mp": "3.6497(96)",
            "mp2": "4.74(13)",
            "c1": "5.37(39)e+06",
            "c2": "-7.37415914(70)e+6"
        },
        "mass8": {
            "T_strt": 13,
            "T_end": 40,
            "chi2": 1.3651242533619339,
            "Q": 0.06170335427200361,
            "two_state_enabled":1,
            "mp": "3.8297(96)",
            "mp2": "4.74(13)",
            "c1": "5.07(39)e+06",
            "c2": "-7.57415914(70)e+6"
        }
    },
    "ensemble11": {
        "mass0": {
            "T_strt": 6,
            "T_end": 18,
            "chi2": 0.9677480317116541,
            "Q": 0.5047130830886947,
            "two_state_enabled":1,
            "mp": "3.612(11)",
            "mp2": "4.15(15)",
            "c1": "1.56(55)e+06",
            "c2": "-1.3(1.1)e+06"
        }
    },
    "ensemble12": {
        "mass0": {
            "T_strt": 6,
            "T_end": 30,
            "chi2": 0.9677480317116541,
            "Q": 0.5047130830886947,
            "mp": "3.612(11)",
            "mp2": "4.15(15)",
            "c1": "3.26(55)e+06",
            "c2": "-2.4(1.1)e+06"
        }
    },
    "ensemble14": {
        "mass0": {
            "T_strt": 6,
            "T_end": 28,
            "chi2": 0.9677480317116541,
            "Q": 0.5047130830886947,
            "mp": "3.612(11)",
            "mp2": "4.15(15)",
            "c1": "1.96(55)e+07",
            "c2": "-1.6(1.1)e+07"
        },
        "mass7": {
            "T_strt": 6,
            "T_end": 28,
            "chi2": 0.9677480317116541,
            "Q": 0.5047130830886947,
            "mp": "3.712(11)",
            "mp2": "4.15(15)",
            "c1": "1.96(55)e+07",
            "c2": "-1.6(1.1)e+07"
        },
        "mass8": {
            "T_strt": 6,
            "T_end": 28,
            "chi2": 0.9677480317116541,
            "Q": 0.5047130830886947,
            "mp": "3.812(11)",
            "mp2": "4.15(15)",
            "c1": "1.96(55)e+07",
            "c2": "-1.6(1.1)e+07"
        }
    }
}
